Metadata-Version: 2.1
Name: odoo12-addon-account-invoice-default-code-column
Version: 12.0.1.0.1.99.dev1
Summary: Display Default code product in a dedicated column on invoice reports
Home-page: https://github.com/OCA/account-invoicing
Author: GRAP,Odoo Community Association (OCA)
Author-email: support@odoo-community.org
License: AGPL-3
Platform: UNKNOWN
Classifier: Programming Language :: Python
Classifier: Framework :: Odoo
Classifier: Framework :: Odoo :: 12.0
Classifier: License :: OSI Approved :: GNU Affero General Public License v3
Requires-Python: >=3.5
Requires-Dist: odoo <12.1dev,>=12.0a
